{
  "format": 1,
  "types": [
    {
      "value": "fix",
      "description": "Bug(s) correction"
    },
    {
      "value": "feat",
      "description": "New feature(s)"
    },
    {
      "value": "core",
      "description": "Change(s) on the application core"
    },
    {
      "value": "test",
      "description": "Change(s) related to tests"
    },
    {
      "value": "doc",
      "description": "Documentation / comment(s)"
    }
  ],
  "minLength": 8,
  "maxLengt": 70,
  "changeVersion": "never",
  "showAllVersionTypes": false,
  "stageAllChanges": false
}